npong/__init__.py
npong/__main__.py
npong-1.13.dist-info/licenses/LICENSE
npong-1.13.dist-info/METADATA
npong-1.13.dist-info/WHEEL
npong-1.13.dist-info/entry_points.txt
npong-1.13.dist-info/top_level.txt
npong-1.13.dist-info/RECORD
