Metadata-Version: 2.4
Name: npong
Version: 1.13
Summary: Pong in Python, now with curses!
Author-email: Jacobus Burger <therealjacoburger@gmail.com>
Maintainer-email: Jacobus Burger <therealjacoburger@gmail.com>
License-Expression: MIT
Project-URL: Repository, https://github.com/LordUbuntu/pong-ncurses
Keywords: pong,game,ncurses,curses
Classifier: Development Status :: 6 - Mature
Classifier: Operating System :: OS Independent
Classifier: Environment :: Console :: Curses
Classifier: Topic :: Games/Entertainment :: Arcade
Classifier: Intended Audience :: Developers
Classifier: Intended Audience :: Education
Classifier: Intended Audience :: End Users/Desktop
Classifier: Intended Audience :: Other Audience
Classifier: Programming Language :: Python :: 3
Classifier: Programming Language :: Python :: 3.13
Classifier: Programming Language :: Python :: Implementation :: CPython
Requires-Python: >=3.13.3
License-File: LICENSE
Requires-Dist: windows-curses; platform_system == "Windows"
Dynamic: license-file
